cq_extrusions/__init__.py
cq_extrusions/vslot.py
cq_extrusions-0.0.1.dist-info/LICENSE
cq_extrusions-0.0.1.dist-info/METADATA
cq_extrusions-0.0.1.dist-info/WHEEL
cq_extrusions-0.0.1.dist-info/top_level.txt
cq_extrusions-0.0.1.dist-info/RECORD
