Metadata-Version: 2.1
Name: cq-extrusions
Version: 0.0.1
Summary: A CadQuery library of extrusions
Author-email: James Keal <james@keal.au>
Project-URL: Github, https://github.com/keeeal/cq-extrusions
Classifier: Programming Language :: Python :: 3
Classifier: License :: OSI Approved :: MIT License
Classifier: Operating System :: OS Independent
License-File: LICENSE
Requires-Dist: cadquery >=2.4.0
